Metadata-Version: 2.1
Name: pygitclone
Version: 0.0.3
Summary: Gitclone allows you to manage multiple git repositories in a directory structure with ease
Home-page: https://github.com/evyli/gitclone
Author: Leah Lackner
Author-email: leah.lackner+github@gmail.com
License: GPLv3
Project-URL: Documentation, https://github.com/evyli/gitclone/blob/master/README.md#gitclone
Project-URL: Source, https://github.com/evyli/gitclone
Project-URL: Tracker, https://github.com/evyli/gitclone/issues
Platform: Linux
Platform: Mac OSX
Classifier: Development Status :: 2 - Pre-Alpha
Classifier: Environment :: Console
Classifier: Intended Audience :: Developers
Classifier: License :: OSI Approved :: GNU General Public License v3 or later (GPLv3+)
Classifier: Operating System :: MacOS :: MacOS X
Classifier: Operating System :: POSIX :: Linux
Classifier: Programming Language :: Python :: 3.10
Requires-Python: >=3.10
Provides-Extra: dev
License-File: LICENSE
